wikijs/__init__.py
wikijs/admin.py
wikijs/app_settings.py
wikijs/auth_hooks.py
wikijs/manager.py
wikijs/models.py
wikijs/queries.py
wikijs/tasks.py
wikijs/test.py
wikijs/urls.py
wikijs/views.py
wikijs/cogs/__init__.py
wikijs/cogs/wikijs.py
wikijs/locale/de/LC_MESSAGES/django.po
wikijs/locale/en/LC_MESSAGES/django.mo
wikijs/locale/en/LC_MESSAGES/django.po
wikijs/migrations/0001_initial.py
wikijs/migrations/0002_auto_20200615_0932.py
wikijs/migrations/__init__.py
allianceauth_wiki_js-0.1.0.dist-info/LICENSE
allianceauth_wiki_js-0.1.0.dist-info/WHEEL
allianceauth_wiki_js-0.1.0.dist-info/METADATA
allianceauth_wiki_js-0.1.0.dist-info/RECORD
