Metadata-Version: 2.1
Name: allianceauth-wiki-js
Version: 0.1.0
Summary: Simple User and group management for Wiki JS as a service of AllianceAuth
Keywords: allianceauth,eveonline
Author-email: AaronKable <aaronkable@gmail.com>
Requires-Python: >=3.8
Classifier: Environment :: Web Environment
Classifier: Framework :: Celery
Classifier: Framework :: Django
Classifier: Framework :: Django :: 4.0
Classifier: Framework :: Django :: 4.2
Classifier: Intended Audience :: Developers
Classifier: License :: OSI Approved :: GNU General Public License v3 (GPLv3)
Classifier: Operating System :: OS Independent
Classifier: Programming Language :: Python
Classifier: Programming Language :: Python :: 3 :: Only
Classifier: Programming Language :: Python :: 3.8
Classifier: Programming Language :: Python :: 3.9
Classifier: Programming Language :: Python :: 3.10
Classifier: Programming Language :: Python :: 3.11
Classifier: Programming Language :: Python :: 3.12
Classifier: Programming Language :: Python :: Implementation :: CPython
Classifier: Topic :: Internet :: WWW/HTTP
Classifier: Topic :: Internet :: WWW/HTTP :: Dynamic Content
Requires-Dist: allianceauth<5.0.0,>=3
Requires-Dist: graphqlclient
Requires-Dist: allianceauth-discordbot>=3.0.0 ; extra == "discordbot"
Project-URL: Homepage, https://github.com/Solar-Helix-Independent-Transport/allianceauth-wiki-js
Project-URL: Source, https://github.com/Solar-Helix-Independent-Transport/allianceauth-wiki-js
Project-URL: Tracker, https://github.com/Solar-Helix-Independent-Transport/allianceauth-wiki-js/issues
Provides-Extra: discordbot
